homeserver/__init__.py
homeserver-0.0.1.dist-info/METADATA
homeserver-0.0.1.dist-info/WHEEL
homeserver-0.0.1.dist-info/top_level.txt
homeserver-0.0.1.dist-info/RECORD
