Metadata-Version: 2.1
Name: homeserver
Version: 0.0.1
Summary: Self-hosting for Python devs who love Matrix.
Home-page: http://github.com/username/my_package
Author: Mo Balaa
Author-email: balaa@fractalnetworks.co
License: AGPLv3
Classifier: License :: OSI Approved :: GNU Affero General Public License v3
Classifier: Programming Language :: Python
Classifier: Programming Language :: Python :: 3
Classifier: Programming Language :: Python :: 3.6
Classifier: Programming Language :: Python :: 3.7
Classifier: Programming Language :: Python :: 3.8
